openbb_platform_pro_backend/__init__.py
openbb_platform_pro_backend/main.py
openbb_platform_pro_backend/utils.py
openbb_platform_pro_backend-1.1.0.dist-info/METADATA
openbb_platform_pro_backend-1.1.0.dist-info/WHEEL
openbb_platform_pro_backend-1.1.0.dist-info/entry_points.txt
openbb_platform_pro_backend-1.1.0.dist-info/RECORD
