Metadata-Version: 2.1
Name: openbb-platform-pro-backend
Version: 1.1.0
Summary: Widgets JSON for OpenBB Terminal Pro
Author: OpenBB Team
Author-email: hello@openbb.co
Requires-Python: >=3.9,<3.13
Classifier: Programming Language :: Python :: 3
Classifier: Programming Language :: Python :: 3.9
Classifier: Programming Language :: Python :: 3.10
Classifier: Programming Language :: Python :: 3.11
Classifier: Programming Language :: Python :: 3.12
Requires-Dist: openbb-charting (>=2.2.0,<3.0.0)
Requires-Dist: openbb_core (>=1.3.0,<2.0.0)
